AUTHORS
HISTORY
LICENSE
MANIFEST.in
README
TODO
ez_setup.py
setup.py
PyMos.egg-info/PKG-INFO
PyMos.egg-info/SOURCES.txt
PyMos.egg-info/dependency_links.txt
PyMos.egg-info/requires.txt
PyMos.egg-info/top_level.txt
bin/pymos
pymos/__init__.py
pymos/core.py