Metadata-Version: 1.0
Name: PyMos
Version: 0.6.3
Summary: Python Mosaic Generator
Home-page: UNKNOWN
Author: Abhishek Mishra (ideamonk), Yuvi (yuvipanda)
Author-email: ideamonk@gmail.com, me@yuvi.in
License: BSD
Keywords: mosaic imaging graphics poster
Platform: UNKNOWN
